{"meta":{"code":200,"errorType":"deprecated","errorDetail":"Please provide an API version to avoid future errors.See http:\/\/bit.ly\/vywCav"},"response":{"venue":{"id":"4bd79a1a304fce7239c033ab","name":"Bay Park Resort Hotel","contact":{"phone":"+556130373000","formattedPhone":"+55 61 3037-3000"},"location":{"address":"SHTN Trecho 2 Lt. 5","lat":-15.78419304543496,"lng":-47.85357803106308,"postalCode":"70327-900","city":"Brasília","state":"DF","country":"Brazil","cc":"BR"},"canonicalUrl":"https:\/\/foursquare.com\/v\/bay-park-resort-hotel\/4bd79a1a304fce7239c033ab","categories":[{"id":"4bf58dd8d48988d1fa931735","name":"Hotel","pluralName":"Hotels","shortName":"Hotel","icon":"https:\/\/foursquare.com\/img\/categories\/travel\/hotel.png","parents":["Travel & Transport"],"primary":true}],"verified":false,"restricted":true,"stats":{"checkinsCount":614,"usersCount":386,"tipCount":58},"url":"http:\/\/www.baypark.com.br","likes":{"count":0,"groups":[]},"rating":7.97,"specials":[],"photos":{"count":37,"groups":[{"type":"checkin","name":"Friends' check-in photos","count":0,"items":[]},{"type":"venue","name":"Venue photos","count":37,"items":[{"id":"5108804be4b0dbd544f2e80f","createdAt":1359511627,"source":{"name":"foursquare for iPhone","url":"https:\/\/foursquare.com\/download\/#\/iphone"},"url":"https:\/\/is1.4sqi.net\/pix\/33893539_bMgiivxcWNHtUSIjDQHdyRr4xVLVPmrwIrGwnHyIjEo.jpg","sizes":{"count":4,"items":[{"url":"https:\/\/is1.4sqi.net\/pix\/33893539_bMgiivxcWNHtUSIjDQHdyRr4xVLVPmrwIrGwnHyIjEo.jpg","width":720,"height":960},{"url":"https:\/\/is0.4sqi.net\/derived_pix\/33893539_bMgiivxcWNHtUSIjDQHdyRr4xVLVPmrwIrGwnHyIjEo_300x300.jpg","width":300,"height":300},{"url":"https:\/\/is0.4sqi.net\/derived_pix\/33893539_bMgiivxcWNHtUSIjDQHdyRr4xVLVPmrwIrGwnHyIjEo_100x100.jpg","width":100,"height":100},{"url":"https:\/\/is0.4sqi.net\/derived_pix\/33893539_bMgiivxcWNHtUSIjDQHdyRr4xVLVPmrwIrGwnHyIjEo_36x36.jpg","width":36,"height":36}]},"user":{"id":"33893539","firstName":"Lisandra","gender":"female","photo":"https:\/\/is0.4sqi.net\/userpix_thumbs\/WNZ2QC4IGEI0V0WF.jpg","tips":{"count":2},"homeCity":"São Paulo","bio":"","contact":{}},"visibility":"public"},{"id":"50f52c24e4b0720a5bcdcbf0","createdAt":1358244900,"source":{"name":"foursquare for iPhone","url":"https:\/\/foursquare.com\/download\/#\/iphone"},"url":"https:\/\/is0.4sqi.net\/pix\/19588954_w0aRHEhiKyu_bzckKM2rBSe8CmtuymC3CLn-e6ARNSY.jpg","sizes":{"count":4,"items":[{"url":"https:\/\/is0.4sqi.net\/pix\/19588954_w0aRHEhiKyu_bzckKM2rBSe8CmtuymC3CLn-e6ARNSY.jpg","width":959,"height":717},{"url":"https:\/\/is1.4sqi.net\/derived_pix\/19588954_w0aRHEhiKyu_bzckKM2rBSe8CmtuymC3CLn-e6ARNSY_300x300.jpg","width":300,"height":300},{"url":"https:\/\/is1.4sqi.net\/derived_pix\/19588954_w0aRHEhiKyu_bzckKM2rBSe8CmtuymC3CLn-e6ARNSY_100x100.jpg","width":100,"height":100},{"url":"https:\/\/is1.4sqi.net\/derived_pix\/19588954_w0aRHEhiKyu_bzckKM2rBSe8CmtuymC3CLn-e6ARNSY_36x36.jpg","width":36,"height":36}]},"user":{"id":"19588954","firstName":"Waldecir","lastName":"d.","gender":"male","photo":"https:\/\/is0.4sqi.net\/userpix_thumbs\/RYTIWMIKZOLYUXEH.jpg","tips":{"count":14},"lists":{"groups":[{"type":"created","count":1,"items":[]}]},"homeCity":"São Paulo, Brasil","bio":"","contact":{}},"visibility":"public"},{"id":"50c4b87fe4b07819222c6906","createdAt":1355069567,"source":{"name":"foursquare for iPhone","url":"https:\/\/foursquare.com\/download\/#\/iphone"},"url":"https:\/\/is0.4sqi.net\/pix\/28832511_kgYItg91PCYeZwycUe9XbIIoSj-FabINbdLsyUR6sRA.jpg","sizes":{"count":4,"items":[{"url":"https:\/\/is0.4sqi.net\/pix\/28832511_kgYItg91PCYeZwycUe9XbIIoSj-FabINbdLsyUR6sRA.jpg","width":540,"height":720},{"url":"https:\/\/is1.4sqi.net\/derived_pix\/28832511_kgYItg91PCYeZwycUe9XbIIoSj-FabINbdLsyUR6sRA_300x300.jpg","width":300,"height":300},{"url":"https:\/\/is1.4sqi.net\/derived_pix\/28832511_kgYItg91PCYeZwycUe9XbIIoSj-FabINbdLsyUR6sRA_100x100.jpg","width":100,"height":100},{"url":"https:\/\/is1.4sqi.net\/derived_pix\/28832511_kgYItg91PCYeZwycUe9XbIIoSj-FabINbdLsyUR6sRA_36x36.jpg","width":36,"height":36}]},"user":{"id":"28832511","firstName":"André","lastName":"F.","gender":"male","photo":"https:\/\/is0.4sqi.net\/userpix_thumbs\/DUBJCNDST4NXG4TP.jpg","tips":{"count":5},"homeCity":"São Paulo, Brazil","bio":"","contact":{}},"visibility":"public"},{"id":"50bf2521e4b0a04b0ea9784a","createdAt":1354704161,"source":{"name":"foursquare for iPhone","url":"https:\/\/foursquare.com\/download\/#\/iphone"},"url":"https:\/\/is0.4sqi.net\/pix\/35532488_fRhfHgmpo_ndZu4J-2gU5tKUro2VkcJfS3TDL5q9FnE.jpg","sizes":{"count":4,"items":[{"url":"https:\/\/is0.4sqi.net\/pix\/35532488_fRhfHgmpo_ndZu4J-2gU5tKUro2VkcJfS3TDL5q9FnE.jpg","width":720,"height":540},{"url":"https:\/\/is1.4sqi.net\/derived_pix\/35532488_fRhfHgmpo_ndZu4J-2gU5tKUro2VkcJfS3TDL5q9FnE_300x300.jpg","width":300,"height":300},{"url":"https:\/\/is1.4sqi.net\/derived_pix\/35532488_fRhfHgmpo_ndZu4J-2gU5tKUro2VkcJfS3TDL5q9FnE_100x100.jpg","width":100,"height":100},{"url":"https:\/\/is1.4sqi.net\/derived_pix\/35532488_fRhfHgmpo_ndZu4J-2gU5tKUro2VkcJfS3TDL5q9FnE_36x36.jpg","width":36,"height":36}]},"user":{"id":"35532488","firstName":"Roberto","lastName":"S.","gender":"male","photo":"https:\/\/is1.4sqi.net\/userpix_thumbs\/JEN3O3Y4QI5BTVL1.jpg","tips":{"count":0},"homeCity":"São Paulo","bio":"Assessor Parlamentar da Deputada Federal Keiko  Ota\r\n; Amo  Nosso Brasil, amo São Paulo, Coordenação Geral do Festival do Japão; Voluntariado; Fazer diferença","contact":{}},"visibility":"public"},{"id":"50bd0349e4b0c5a282d19c77","createdAt":1354564425,"source":{"name":"foursquare for iPhone","url":"https:\/\/foursquare.com\/download\/#\/iphone"},"url":"https:\/\/is0.4sqi.net\/pix\/28832511_D9JFGaJUk1P-4OiruT43emIIGbpIWfgBdT1fl40DVeA.jpg","sizes":{"count":4,"items":[{"url":"https:\/\/is0.4sqi.net\/pix\/28832511_D9JFGaJUk1P-4OiruT43emIIGbpIWfgBdT1fl40DVeA.jpg","width":720,"height":540},{"url":"https:\/\/is1.4sqi.net\/derived_pix\/28832511_D9JFGaJUk1P-4OiruT43emIIGbpIWfgBdT1fl40DVeA_300x300.jpg","width":300,"height":300},{"url":"https:\/\/is1.4sqi.net\/derived_pix\/28832511_D9JFGaJUk1P-4OiruT43emIIGbpIWfgBdT1fl40DVeA_100x100.jpg","width":100,"height":100},{"url":"https:\/\/is1.4sqi.net\/derived_pix\/28832511_D9JFGaJUk1P-4OiruT43emIIGbpIWfgBdT1fl40DVeA_36x36.jpg","width":36,"height":36}]},"user":{"id":"28832511","firstName":"André","lastName":"F.","gender":"male","photo":"https:\/\/is0.4sqi.net\/userpix_thumbs\/DUBJCNDST4NXG4TP.jpg","tips":{"count":5},"homeCity":"São Paulo, Brazil","bio":"","contact":{}},"visibility":"public"},{"id":"50bc01dae4b0de82eaeda1ed","createdAt":1354498522,"source":{"name":"foursquare for iPhone","url":"https:\/\/foursquare.com\/download\/#\/iphone"},"url":"https:\/\/is0.4sqi.net\/pix\/28832511_yEpLrBZWqjX201HojITPqDANd7HRXQywzPFHiagfjJ8.jpg","sizes":{"count":4,"items":[{"url":"https:\/\/is0.4sqi.net\/pix\/28832511_yEpLrBZWqjX201HojITPqDANd7HRXQywzPFHiagfjJ8.jpg","width":720,"height":540},{"url":"https:\/\/is1.4sqi.net\/derived_pix\/28832511_yEpLrBZWqjX201HojITPqDANd7HRXQywzPFHiagfjJ8_300x300.jpg","width":300,"height":300},{"url":"https:\/\/is1.4sqi.net\/derived_pix\/28832511_yEpLrBZWqjX201HojITPqDANd7HRXQywzPFHiagfjJ8_100x100.jpg","width":100,"height":100},{"url":"https:\/\/is1.4sqi.net\/derived_pix\/28832511_yEpLrBZWqjX201HojITPqDANd7HRXQywzPFHiagfjJ8_36x36.jpg","width":36,"height":36}]},"user":{"id":"28832511","firstName":"André","lastName":"F.","gender":"male","photo":"https:\/\/is0.4sqi.net\/userpix_thumbs\/DUBJCNDST4NXG4TP.jpg","tips":{"count":5},"homeCity":"São Paulo, Brazil","bio":"","contact":{}},"visibility":"public"}]}],"summary":"37 photos"},"hereNow":{"count":0,"summary":"0 people here","groups":[]},"createdAt":1272420890,"mayor":{"count":12,"user":{"id":"28832511","firstName":"André","lastName":"F.","gender":"male","photo":"https:\/\/is0.4sqi.net\/userpix_thumbs\/DUBJCNDST4NXG4TP.jpg","tips":{"count":5},"homeCity":"São Paulo, Brazil","bio":"","contact":{}}},"tips":{"count":58,"groups":[{"type":"others","name":"Tips from others","count":20,"items":[{"id":"4e8142579adf504a0e0f644a","createdAt":1317093975,"text":"Nao se hospede! Hotel decadente, sujo, funcionários mal educados! Localização ruim!","canonicalUrl":"https:\/\/foursquare.com\/item\/4e8142579adf504a0e0f644a","likes":{"count":0,"groups":[]},"todo":{"count":0},"done":{"count":3},"user":{"id":"6593221","firstName":"Cassi","lastName":"D.","gender":"female","photo":"https:\/\/is0.4sqi.net\/userpix_thumbs\/RBVOBPQNZN0IW1XE.jpg","tips":{"count":33},"homeCity":"São Paulo, Brasil","bio":"","contact":{}}},{"id":"4ffeb692e4b0012e5314015d","createdAt":1342092946,"text":"Terrível atendimento, lugar horroroso, os lençóis parecem estar sujos, o frigobar é uma geladeira velha horrorosa!! Só fique senão tiver outra opção, como eu!","canonicalUrl":"https:\/\/foursquare.com\/item\/4ffeb692e4b0012e5314015d","likes":{"count":0,"groups":[]},"todo":{"count":0},"done":{"count":1},"user":{"id":"29015598","firstName":"Silvia","lastName":"C.","gender":"female","photo":"https:\/\/is0.4sqi.net\/userpix_thumbs\/PJDLOVVIQMEILW0M.jpg","tips":{"count":4},"homeCity":"Tocantins","bio":"","contact":{}}},{"id":"4de158041f6e3190ccf5c7cd","createdAt":1306613764,"text":"Medo!!! O pior hotel da minha vida!!","canonicalUrl":"https:\/\/foursquare.com\/item\/4de158041f6e3190ccf5c7cd","photo":{"id":"4de15808a12d480b8d6b7e35","createdAt":1306613768,"source":{"name":"foursquare for Android","url":"https:\/\/foursquare.com\/download\/#\/android"},"url":"https:\/\/is0.4sqi.net\/pix\/P21YBHDJT15EU5DXYZWMKKP14Q1SIWSD52XPDI0G34D4AAQY.jpg","sizes":{"count":4,"items":[{"url":"https:\/\/is0.4sqi.net\/pix\/P21YBHDJT15EU5DXYZWMKKP14Q1SIWSD52XPDI0G34D4AAQY.jpg","width":720,"height":540},{"url":"https:\/\/is1.4sqi.net\/derived_pix\/P21YBHDJT15EU5DXYZWMKKP14Q1SIWSD52XPDI0G34D4AAQY_300x300.jpg","width":300,"height":300},{"url":"https:\/\/is1.4sqi.net\/derived_pix\/P21YBHDJT15EU5DXYZWMKKP14Q1SIWSD52XPDI0G34D4AAQY_100x100.jpg","width":100,"height":100},{"url":"https:\/\/is1.4sqi.net\/derived_pix\/P21YBHDJT15EU5DXYZWMKKP14Q1SIWSD52XPDI0G34D4AAQY_36x36.jpg","width":36,"height":36}]}},"photourl":"https:\/\/irs2.4sqi.net\/img\/general\/original\/P21YBHDJT15EU5DXYZWMKKP14Q1SIWSD52XPDI0G34D4AAQY.jpg","likes":{"count":0,"groups":[]},"todo":{"count":0},"done":{"count":2},"user":{"id":"6097570","firstName":"Henrique","lastName":"L.","gender":"male","photo":"https:\/\/is0.4sqi.net\/userpix_thumbs\/0OPQD1ZZI4YRAE4S.jpg","tips":{"count":7},"homeCity":"São Paulo, Brasil","bio":"","contact":{}}},{"id":"4db7fdce6a238ed5d8e9f191","createdAt":1303903694,"text":"Péssimo atendimento. Meia hora pra fazer checkin às 11 da noite. Café da manhã fraquíssimo. Se tiverem opção, evitem este.","canonicalUrl":"https:\/\/foursquare.com\/item\/4db7fdce6a238ed5d8e9f191","likes":{"count":0,"groups":[]},"todo":{"count":0},"done":{"count":2},"user":{"id":"2547253","firstName":"Alex","lastName":"S.","gender":"male","photo":"https:\/\/is1.4sqi.net\/userpix_thumbs\/NNO0HQRI3K2DWWTN.jpg","tips":{"count":10},"homeCity":"Belo Horizonte, Brasil","bio":"","contact":{}}},{"id":"4d925b3652ed224b71e905ac","createdAt":1301437238,"text":"Primeira impressão: péssimo atendimento e nao tem nada perto, fujam!!!","canonicalUrl":"https:\/\/foursquare.com\/item\/4d925b3652ed224b71e905ac","likes":{"count":0,"groups":[]},"todo":{"count":0},"done":{"count":2},"user":{"id":"6510125","firstName":"Thiago","lastName":"S.","gender":"male","photo":"https:\/\/is1.4sqi.net\/userpix_thumbs\/U2SPBMIDPUOLJQAW.jpg","tips":{"count":45},"lists":{"groups":[{"type":"created","count":4,"items":[]}]},"homeCity":"São Paulo, Brasil","bio":"","contact":{}}},{"id":"50be7ccde4b0b1f5d57003aa","createdAt":1354661069,"text":"CORRA!!!! Hotel decrépito, funcionários sem treinamento, serviço de quarto nao existe (nao da pra chamar aquilo de serviço). Quem já se hospedou nao volta!","canonicalUrl":"https:\/\/foursquare.com\/item\/50be7ccde4b0b1f5d57003aa","likes":{"count":0,"groups":[]},"todo":{"count":0},"done":{"count":1},"user":{"id":"6737644","firstName":"Jonathan","lastName":"C.","gender":"male","photo":"https:\/\/is1.4sqi.net\/userpix_thumbs\/UXWRTFOQTRWGGAMJ.jpg","tips":{"count":12},"homeCity":"João Pessoa, Brasil","bio":"","contact":{}}},{"id":"50a4dceee4b0d9744ee22b09","createdAt":1352981742,"text":"Parece ter melhorado um pouco. Todo hotel parece ter sido reformado e outra parte ainda esta em reforma. Quase nao tem funcionários, mas fomos bem atendidos no Cafe. Um hotel de boa pra mim!","canonicalUrl":"https:\/\/foursquare.com\/item\/50a4dceee4b0d9744ee22b09","likes":{"count":0,"groups":[]},"todo":{"count":0},"done":{"count":1},"user":{"id":"14281323","firstName":"Azzis","lastName":"N.","gender":"male","photo":"https:\/\/is1.4sqi.net\/userpix_thumbs\/H4HRIQPCM0L2UO3J.jpg","tips":{"count":9},"homeCity":"São Paulo, Brasil","bio":"","contact":{}}},{"id":"4f98a0a0e4b0fc88e72c6da6","createdAt":1335402656,"text":"Se ler essa dica a tempo, não se hospede!","canonicalUrl":"https:\/\/foursquare.com\/item\/4f98a0a0e4b0fc88e72c6da6","likes":{"count":0,"groups":[]},"todo":{"count":0},"done":{"count":1},"user":{"id":"12234296","firstName":"Rodrigo","lastName":"R.","gender":"male","photo":"https:\/\/is0.4sqi.net\/userpix_thumbs\/QYDRW4PIU0MRHW0U.jpg","tips":{"count":12},"homeCity":"São Paulo, Brasil","bio":"","contact":{}}},{"id":"4f4039dee4b0c80f8355c078","createdAt":1329609182,"text":"Gostei daqui, piscina perfeita! Vista linda e pertíssimo do Iate Club! So nao gostei da lentidao dos funcionarios na hora do Check-in.","canonicalUrl":"https:\/\/foursquare.com\/item\/4f4039dee4b0c80f8355c078","likes":{"count":0,"groups":[]},"todo":{"count":0},"done":{"count":1},"user":{"id":"20289642","firstName":"Abraao","lastName":"B.","gender":"male","photo":"https:\/\/is0.4sqi.net\/userpix_thumbs\/MPITVNEEB0VDSSUW.jpg","tips":{"count":4},"homeCity":"Brasilia - DF","bio":"","contact":{}}},{"id":"4bca2af870c603bb053a98b4","createdAt":1271540472,"text":"Vire a torneira para esquerda para ter agua quente.. Inclusive na pia e todo lugar!","canonicalUrl":"https:\/\/foursquare.com\/item\/4bca2af870c603bb053a98b4","likes":{"count":0,"groups":[]},"todo":{"count":0},"done":{"count":2},"user":{"id":"756450","firstName":"Raphael","lastName":"F.","gender":"male","photo":"https:\/\/is0.4sqi.net\/userpix_thumbs\/ETJVRC2PV0AAW41T.jpg","tips":{"count":14},"homeCity":"São Paulo, SP","bio":"","contact":{}}},{"id":"5102adabe4b08a440b689b1f","createdAt":1359130027,"text":"Isso aqui é padecer no inferno mesmo.","canonicalUrl":"https:\/\/foursquare.com\/item\/5102adabe4b08a440b689b1f","likes":{"count":0,"groups":[]},"todo":{"count":0},"done":{"count":0},"user":{"id":"6429441","firstName":"Alvaro","lastName":"N.","gender":"male","photo":"https:\/\/is0.4sqi.net\/userpix_thumbs\/IMTMFFM0F53WN54X.jpg","tips":{"count":16},"homeCity":"Brasília, DF","bio":"Advogado da União, Consultoria Jurídica do Ministério da Educação Brasília.","contact":{}}},{"id":"5102ad5de4b0ae12b300fdaa","createdAt":1359129949,"text":"Olhando a chuva.","canonicalUrl":"https:\/\/foursquare.com\/item\/5102ad5de4b0ae12b300fdaa","likes":{"count":0,"groups":[]},"todo":{"count":0},"done":{"count":1},"user":{"id":"6429441","firstName":"Alvaro","lastName":"N.","gender":"male","photo":"https:\/\/is0.4sqi.net\/userpix_thumbs\/IMTMFFM0F53WN54X.jpg","tips":{"count":16},"homeCity":"Brasília, DF","bio":"Advogado da União, Consultoria Jurídica do Ministério da Educação Brasília.","contact":{}}},{"id":"50ed404ae4b01c686e8143d2","createdAt":1357725770,"text":"Um dos piores hotéis que já fiquei na minha vida. Eles se esquecem de arrumar o quarto. Péssimo","canonicalUrl":"https:\/\/foursquare.com\/item\/50ed404ae4b01c686e8143d2","likes":{"count":0,"groups":[]},"todo":{"count":0},"done":{"count":0},"user":{"id":"9997803","firstName":"Michel","lastName":"H.","gender":"male","photo":"https:\/\/is1.4sqi.net\/userpix_thumbs\/ZDYURJW4HDPRR23W.jpg","tips":{"count":78},"homeCity":"São Paulo, Brasil","bio":"","contact":{}}},{"id":"50ca7a12e4b0cbbcc2e6e7ea","createdAt":1355446802,"text":"Que fria. Não recomendo","canonicalUrl":"https:\/\/foursquare.com\/item\/50ca7a12e4b0cbbcc2e6e7ea","likes":{"count":0,"groups":[]},"todo":{"count":0},"done":{"count":1},"user":{"id":"4478266","firstName":"Rafa","lastName":"S.","gender":"male","photo":"https:\/\/is0.4sqi.net\/userpix_thumbs\/YD45WUYG42TRKTDK.jpg","tips":{"count":9},"homeCity":"Curitiba, Brasil","bio":"","contact":{}}},{"id":"50be546de4b0134f49fbae8a","createdAt":1354650733,"text":"Táxi aqui é difícil, demora...","canonicalUrl":"https:\/\/foursquare.com\/item\/50be546de4b0134f49fbae8a","likes":{"count":0,"groups":[]},"todo":{"count":0},"done":{"count":1},"user":{"id":"28832511","firstName":"André","lastName":"F.","gender":"male","photo":"https:\/\/is0.4sqi.net\/userpix_thumbs\/DUBJCNDST4NXG4TP.jpg","tips":{"count":5},"homeCity":"São Paulo, Brazil","bio":"","contact":{}}},{"id":"50b734bde4b0620488ed1a4d","createdAt":1354183869,"text":"O quarto é limpo e confortável, inclusive com sacada. Ruim mesmo (mas muito ruim mesmo) é o atendimento lento e com pessoal não treinado.","canonicalUrl":"https:\/\/foursquare.com\/item\/50b734bde4b0620488ed1a4d","likes":{"count":0,"groups":[]},"todo":{"count":0},"done":{"count":1},"user":{"id":"26642189","firstName":"Daniel","lastName":"H.","gender":"male","photo":"https:\/\/is0.4sqi.net\/userpix_thumbs\/TAZVOZ2GM4X04L1K.jpg","tips":{"count":9},"homeCity":"Curitiba, Brazil","bio":"","contact":{}}},{"id":"50aebe21e4b00b39bc3fac34","createdAt":1353629217,"text":"Ahhh esquece em chamar qualquer ramal pelo tel do quarto. Vai morrer esperando e tentando rs!","canonicalUrl":"https:\/\/foursquare.com\/item\/50aebe21e4b00b39bc3fac34","likes":{"count":0,"groups":[]},"todo":{"count":0},"done":{"count":1},"user":{"id":"12478120","firstName":"Rafael","lastName":"S.","gender":"male","photo":"https:\/\/is0.4sqi.net\/userpix_thumbs\/2WWKRTDYI2JSJFGM.jpg","tips":{"count":26},"homeCity":"São Paulo, Brasil","bio":"","contact":{}}},{"id":"50aebdb7e4b04cb0a124457d","createdAt":1353629111,"text":"O lugar é mal conservado e cheio de pernilongos. O Quarto é básico e limpo. O atendimento é horrível, funcionários mal treinados, a academia só abre às 18h30 e o serviço de despertar não existe.","canonicalUrl":"https:\/\/foursquare.com\/item\/50aebdb7e4b04cb0a124457d","likes":{"count":0,"groups":[]},"todo":{"count":0},"done":{"count":1},"user":{"id":"12478120","firstName":"Rafael","lastName":"S.","gender":"male","photo":"https:\/\/is0.4sqi.net\/userpix_thumbs\/2WWKRTDYI2JSJFGM.jpg","tips":{"count":26},"homeCity":"São Paulo, Brasil","bio":"","contact":{}}},{"id":"50a5bfd5e4b0573e09b7e483","createdAt":1353039829,"text":"Hotel bacana. Bom custo benefício. Deverá melhorar muito após a reforma","canonicalUrl":"https:\/\/foursquare.com\/item\/50a5bfd5e4b0573e09b7e483","likes":{"count":0,"groups":[]},"todo":{"count":0},"done":{"count":1},"user":{"id":"3193975","firstName":"Leo","lastName":"D.","gender":"male","photo":"https:\/\/is0.4sqi.net\/userpix_thumbs\/DLTXOLTXB14QPDYT.jpg","tips":{"count":6},"homeCity":"Belo Horizonte, Brasil","bio":"","contact":{}}},{"id":"4fd8a22ee4b070de17ff76a6","createdAt":1339597358,"text":"Hotel que a Gol colocou p gte passar a noite, na mesma categoria da Gol: Decadente!!!","canonicalUrl":"https:\/\/foursquare.com\/item\/4fd8a22ee4b070de17ff76a6","likes":{"count":0,"groups":[]},"todo":{"count":0},"done":{"count":1},"user":{"id":"8159622","firstName":"Eveline","lastName":"F.","gender":"female","photo":"https:\/\/is0.4sqi.net\/userpix_thumbs\/MP5QPHNYEUL4PHGG.jpg","tips":{"count":4},"homeCity":"Brasil","bio":"","contact":{}}}]}]},"tags":[],"shortUrl":"http:\/\/4sq.com\/co2Shz","timeZone":"America\/Sao_Paulo","listed":{"count":0},"pageUpdates":{"count":0,"items":[]}}}}